timecave/__init__.py
timecave/data_characteristics.py
timecave/utils.py
timecave/validation_strategy_metrics.py
timecave/data_generation/__init__.py
timecave/data_generation/_utils.py
timecave/data_generation/frequency_modulation.py
timecave/data_generation/time_series_functions.py
timecave/data_generation/time_series_generation.py
timecave/validation_methods/CV.py
timecave/validation_methods/OOS.py
timecave/validation_methods/__init__.py
timecave/validation_methods/base.py
timecave/validation_methods/markov.py
timecave/validation_methods/prequential.py
timecave/validation_methods/weights.py
timecave-1.0.0.dist-info/LICENSE
timecave-1.0.0.dist-info/METADATA
timecave-1.0.0.dist-info/WHEEL
timecave-1.0.0.dist-info/top_level.txt
timecave-1.0.0.dist-info/RECORD
