Metadata-Version: 2.1
Name: timecave
Version: 1.0.0
Summary: Model validation methods for time series forecasting.
Author-email: Miguel Santos Loureiro <miguel.santos.loureiro@tecnico.ulisboa.pt>, Beatriz Pereira Lourenço <beatriz.p.lourenco@tecnico.ulisboa.pt>
License: Apache License
Project-URL: repository, https://github.com/MiguelLoureiro98/timecave
Keywords: time-series,validation
Classifier: Programming Language :: Python :: 3
Classifier: License :: OSI Approved :: Apache Software License
Classifier: Natural Language :: English
Classifier: Operating System :: OS Independent
Classifier: Topic :: Scientific/Engineering :: Artificial Intelligence
Classifier: Topic :: Software Development :: Libraries :: Python Modules
Classifier: Topic :: Software Development :: Version Control :: Git
Classifier: Intended Audience :: Developers
Classifier: Intended Audience :: Science/Research
Classifier: Intended Audience :: Education
Requires-Python: >=3.10
License-File: LICENSE
Requires-Dist: numpy >=1.26.3
Requires-Dist: pandas >=2.1.4
Requires-Dist: matplotlib >=3.8
Requires-Dist: tsfel ==0.1.7
Provides-Extra: dev
Requires-Dist: black >=24.4.2 ; extra == 'dev'
Requires-Dist: mkdocs >=1.6.0 ; extra == 'dev'
Requires-Dist: mkdocs-material >=9.5.30 ; extra == 'dev'
Requires-Dist: mkdocs-material-extensions >=1.3.1 ; extra == 'dev'
Requires-Dist: mkdocstrings-python >=1.10.5 ; extra == 'dev'
Requires-Dist: mkdocs-autorefs >=1.0.1 ; extra == 'dev'
Requires-Dist: pymdown-extensions >=10.8.1 ; extra == 'dev'
Requires-Dist: build >=1.2.1 ; extra == 'dev'
Requires-Dist: twine >=5.1.1 ; extra == 'dev'
Provides-Extra: exp
Requires-Dist: tensorflow >=2.16.1 ; extra == 'exp'
Requires-Dist: keras >=3.3.3 ; extra == 'exp'
Requires-Dist: scikit-learn >=1.4.0 ; extra == 'exp'
Requires-Dist: statsmodels >=0.14.0 ; extra == 'exp'
